{
  "Bravos": {
    "subtotal": 239920.0,
    "subtotal_online": 164260.0,
    "subtotal_taquilla": 75660.0,
    "subtotal_paquete": 44700.0,
    "subtotal_no_paquete": 195220.0,
    "boletos": 950,
    "boletos_online": 535,
    "boletos_taquilla": 415,
    "boletos_cortesias": 155,
    "boletos_cortesias_online": 0,
    "boletos_cortesias_taquilla": 155,
    "boletos_promocion": 39,
    "boletos_promocion_online": 0,
    "boletos_promocion_taquilla": 39,
    "cortesias_por_persona": [
      {
        "persona": "Oficinas Moral",
        "total": 147,
        "online": 0,
        "taquilla": 147
      },
      {
        "persona": "Administrador Boletomóvil",
        "total": 8,
        "online": 0,
        "taquilla": 8
      }
    ],
    "promocion_por_persona": [
      {
        "persona": "Oficinas Moral",
        "total": 39,
        "online": 0,
        "taquilla": 39
      }
    ],
    "ordenes": 256,
    "ordenes_online": 181,
    "ordenes_taquilla": 75,
    "events": [
      "Juego Inaugural: Guerreros vs Bravos",
      "Paquete Serie Inaugural",
      "Paquete Serie Inaugural Guerreros vs Bravos"
    ],
    "has_paquete": true,
    "first_date": "17/03/2026",
    "last_date": "16/04/2026",
    "duration_days": 30,
    "daily": [
      {
        "date": "2026-03-17",
        "subtotal": 0.0,
        "boletos": 137
      },
      {
        "date": "2026-03-18",
        "subtotal": 28300.0,
        "boletos": 77
      },
      {
        "date": "2026-03-19",
        "subtotal": 6360.0,
        "boletos": 23
      },
      {
        "date": "2026-03-20",
        "subtotal": 5820.0,
        "boletos": 9
      },
      {
        "date": "2026-03-21",
        "subtotal": 240.0,
        "boletos": 2
      },
      {
        "date": "2026-03-22",
        "subtotal": 2760.0,
        "boletos": 10
      },
      {
        "date": "2026-03-23",
        "subtotal": 1860.0,
        "boletos": 8
      },
      {
        "date": "2026-03-24",
        "subtotal": 4380.0,
        "boletos": 14
      },
      {
        "date": "2026-03-25",
        "subtotal": 10860.0,
        "boletos": 37
      },
      {
        "date": "2026-03-26",
        "subtotal": 3000.0,
        "boletos": 6
      },
      {
        "date": "2026-03-27",
        "subtotal": 5010.0,
        "boletos": 12
      },
      {
        "date": "2026-03-28",
        "subtotal": 1560.0,
        "boletos": 6
      },
      {
        "date": "2026-03-29",
        "subtotal": 2340.0,
        "boletos": 9
      },
      {
        "date": "2026-03-30",
        "subtotal": 7200.0,
        "boletos": 18
      },
      {
        "date": "2026-03-31",
        "subtotal": 8340.0,
        "boletos": 24
      },
      {
        "date": "2026-04-01",
        "subtotal": 5400.0,
        "boletos": 24
      },
      {
        "date": "2026-04-02",
        "subtotal": 3450.0,
        "boletos": 10
      },
      {
        "date": "2026-04-03",
        "subtotal": 2820.0,
        "boletos": 11
      },
      {
        "date": "2026-04-04",
        "subtotal": 1500.0,
        "boletos": 5
      },
      {
        "date": "2026-04-05",
        "subtotal": 2940.0,
        "boletos": 11
      },
      {
        "date": "2026-04-06",
        "subtotal": 17670.0,
        "boletos": 59
      },
      {
        "date": "2026-04-07",
        "subtotal": 8460.0,
        "boletos": 40
      },
      {
        "date": "2026-04-08",
        "subtotal": 9660.0,
        "boletos": 25
      },
      {
        "date": "2026-04-09",
        "subtotal": 13020.0,
        "boletos": 44
      },
      {
        "date": "2026-04-10",
        "subtotal": 11010.0,
        "boletos": 28
      },
      {
        "date": "2026-04-11",
        "subtotal": 10080.0,
        "boletos": 31
      },
      {
        "date": "2026-04-12",
        "subtotal": 12420.0,
        "boletos": 36
      },
      {
        "date": "2026-04-13",
        "subtotal": 6840.0,
        "boletos": 23
      },
      {
        "date": "2026-04-14",
        "subtotal": 18180.0,
        "boletos": 71
      },
      {
        "date": "2026-04-15",
        "subtotal": 19290.0,
        "boletos": 73
      },
      {
        "date": "2026-04-16",
        "subtotal": 9150.0,
        "boletos": 67
      }
    ],
    "zonas": {
      "Butaca 1ra Base": {
        "boletos": 268,
        "boletos_pagados": 236,
        "boletos_cortesias": 32,
        "boletos_cortesias_online": 0,
        "boletos_cortesias_taquilla": 32,
        "boletos_promocion": 0,
        "boletos_promocion_online": 0,
        "boletos_promocion_taquilla": 0,
        "subtotal": 49500.0,
        "ticket_promedio": 209.75,
        "boletos_online": 180,
        "subtotal_online": 36720.0,
        "boletos_taquilla": 88,
        "subtotal_taquilla": 12780.0
      },
      "Butaca 3ra Base": {
        "boletos": 122,
        "boletos_pagados": 112,
        "boletos_cortesias": 10,
        "boletos_cortesias_online": 0,
        "boletos_cortesias_taquilla": 10,
        "boletos_promocion": 0,
        "boletos_promocion_online": 0,
        "boletos_promocion_taquilla": 0,
        "subtotal": 39000.0,
        "ticket_promedio": 348.21,
        "boletos_online": 73,
        "subtotal_online": 23700.0,
        "boletos_taquilla": 49,
        "subtotal_taquilla": 15300.0
      },
      "General 1ra Base": {
        "boletos": 4,
        "boletos_pagados": 4,
        "boletos_cortesias": 0,
        "boletos_cortesias_online": 0,
        "boletos_cortesias_taquilla": 0,
        "boletos_promocion": 0,
        "boletos_promocion_online": 0,
        "boletos_promocion_taquilla": 0,
        "subtotal": 400.0,
        "ticket_promedio": 100.0,
        "boletos_online": 4,
        "subtotal_online": 400.0,
        "boletos_taquilla": 0,
        "subtotal_taquilla": 0.0
      },
      "General 3ra Base": {
        "boletos": 28,
        "boletos_pagados": 26,
        "boletos_cortesias": 2,
        "boletos_cortesias_online": 0,
        "boletos_cortesias_taquilla": 2,
        "boletos_promocion": 0,
        "boletos_promocion_online": 0,
        "boletos_promocion_taquilla": 0,
        "subtotal": 3120.0,
        "ticket_promedio": 120.0,
        "boletos_online": 17,
        "subtotal_online": 2040.0,
        "boletos_taquilla": 11,
        "subtotal_taquilla": 1080.0
      },
      "VIP": {
        "boletos": 127,
        "boletos_pagados": 67,
        "boletos_cortesias": 50,
        "boletos_cortesias_online": 0,
        "boletos_cortesias_taquilla": 50,
        "boletos_promocion": 10,
        "boletos_promocion_online": 0,
        "boletos_promocion_taquilla": 10,
        "subtotal": 42000.0,
        "ticket_promedio": 545.45,
        "boletos_online": 62,
        "subtotal_online": 39000.0,
        "boletos_taquilla": 65,
        "subtotal_taquilla": 3000.0
      },
      "Zona Gas Noel Butaca Central": {
        "boletos": 401,
        "boletos_pagados": 311,
        "boletos_cortesias": 61,
        "boletos_cortesias_online": 0,
        "boletos_cortesias_taquilla": 61,
        "boletos_promocion": 29,
        "boletos_promocion_online": 0,
        "boletos_promocion_taquilla": 29,
        "subtotal": 105900.0,
        "ticket_promedio": 311.47,
        "boletos_online": 199,
        "subtotal_online": 62400.0,
        "boletos_taquilla": 202,
        "subtotal_taquilla": 43500.0
      }
    }
  },
  "Caliente": {
    "subtotal": 829290.0,
    "subtotal_online": 359260.0,
    "subtotal_taquilla": 470030.0,
    "subtotal_paquete": 255780.0,
    "subtotal_no_paquete": 573510.0,
    "boletos": 3794,
    "boletos_online": 1564,
    "boletos_taquilla": 2230,
    "boletos_cortesias": 75,
    "boletos_cortesias_online": 0,
    "boletos_cortesias_taquilla": 75,
    "boletos_promocion": 39,
    "boletos_promocion_online": 37,
    "boletos_promocion_taquilla": 2,
    "cortesias_por_persona": [
      {
        "persona": "Juan Carlos",
        "total": 75,
        "online": 0,
        "taquilla": 75
      }
    ],
    "promocion_por_persona": [
      {
        "persona": "Venta en línea",
        "total": 37,
        "online": 37,
        "taquilla": 0
      },
      {
        "persona": "Jazmin Pazos",
        "total": 2,
        "online": 0,
        "taquilla": 2
      }
    ],
    "ordenes": 1187,
    "ordenes_online": 518,
    "ordenes_taquilla": 669,
    "events": [
      "Juego Inaugural: Dorados vs Caliente",
      "Paquete: Juego Inaugural | Dorados vs Caliente"
    ],
    "has_paquete": true,
    "first_date": "30/03/2026",
    "last_date": "16/04/2026",
    "duration_days": 17,
    "daily": [
      {
        "date": "2026-03-30",
        "subtotal": 85000.0,
        "boletos": 133
      },
      {
        "date": "2026-03-31",
        "subtotal": 43100.0,
        "boletos": 69
      },
      {
        "date": "2026-04-01",
        "subtotal": 21060.0,
        "boletos": 38
      },
      {
        "date": "2026-04-02",
        "subtotal": 4900.0,
        "boletos": 9
      },
      {
        "date": "2026-04-03",
        "subtotal": 2200.0,
        "boletos": 5
      },
      {
        "date": "2026-04-04",
        "subtotal": 6300.0,
        "boletos": 9
      },
      {
        "date": "2026-04-05",
        "subtotal": 700.0,
        "boletos": 1
      },
      {
        "date": "2026-04-06",
        "subtotal": 8500.0,
        "boletos": 13
      },
      {
        "date": "2026-04-07",
        "subtotal": 25600.0,
        "boletos": 47
      },
      {
        "date": "2026-04-08",
        "subtotal": 17300.0,
        "boletos": 25
      },
      {
        "date": "2026-04-09",
        "subtotal": 23600.0,
        "boletos": 35
      },
      {
        "date": "2026-04-10",
        "subtotal": 290020.0,
        "boletos": 1283
      },
      {
        "date": "2026-04-11",
        "subtotal": 62900.0,
        "boletos": 324
      },
      {
        "date": "2026-04-12",
        "subtotal": 13550.0,
        "boletos": 65
      },
      {
        "date": "2026-04-13",
        "subtotal": 74800.0,
        "boletos": 462
      },
      {
        "date": "2026-04-14",
        "subtotal": 72710.0,
        "boletos": 495
      },
      {
        "date": "2026-04-15",
        "subtotal": 57650.0,
        "boletos": 538
      },
      {
        "date": "2026-04-16",
        "subtotal": 19400.0,
        "boletos": 243
      }
    ],
    "zonas": {
      "Central": {
        "boletos": 1600,
        "boletos_pagados": 1541,
        "boletos_cortesias": 25,
        "boletos_cortesias_online": 0,
        "boletos_cortesias_taquilla": 25,
        "boletos_promocion": 34,
        "boletos_promocion_online": 33,
        "boletos_promocion_taquilla": 1,
        "subtotal": 505540.0,
        "ticket_promedio": 320.98,
        "boletos_online": 836,
        "subtotal_online": 238260.0,
        "boletos_taquilla": 764,
        "subtotal_taquilla": 267280.0
      },
      "Lateral": {
        "boletos": 1135,
        "boletos_pagados": 1097,
        "boletos_cortesias": 34,
        "boletos_cortesias_online": 0,
        "boletos_cortesias_taquilla": 34,
        "boletos_promocion": 4,
        "boletos_promocion_online": 4,
        "boletos_promocion_taquilla": 0,
        "subtotal": 115900.0,
        "ticket_promedio": 105.27,
        "boletos_online": 303,
        "subtotal_online": 31300.0,
        "boletos_taquilla": 832,
        "subtotal_taquilla": 84600.0
      },
      "Lateral Preferente": {
        "boletos": 804,
        "boletos_pagados": 793,
        "boletos_cortesias": 10,
        "boletos_cortesias_online": 0,
        "boletos_cortesias_taquilla": 10,
        "boletos_promocion": 1,
        "boletos_promocion_online": 0,
        "boletos_promocion_taquilla": 1,
        "subtotal": 147860.0,
        "ticket_promedio": 186.22,
        "boletos_online": 243,
        "subtotal_online": 44380.0,
        "boletos_taquilla": 561,
        "subtotal_taquilla": 103480.0
      },
      "Palco Bronce 1ra": {
        "boletos": 83,
        "boletos_pagados": 83,
        "boletos_cortesias": 0,
        "boletos_cortesias_online": 0,
        "boletos_cortesias_taquilla": 0,
        "boletos_promocion": 0,
        "boletos_promocion_online": 0,
        "boletos_promocion_taquilla": 0,
        "subtotal": 10790.0,
        "ticket_promedio": 130.0,
        "boletos_online": 62,
        "subtotal_online": 8060.0,
        "boletos_taquilla": 21,
        "subtotal_taquilla": 2730.0
      },
      "Palco Bronce 3ra": {
        "boletos": 76,
        "boletos_pagados": 76,
        "boletos_cortesias": 0,
        "boletos_cortesias_online": 0,
        "boletos_cortesias_taquilla": 0,
        "boletos_promocion": 0,
        "boletos_promocion_online": 0,
        "boletos_promocion_taquilla": 0,
        "subtotal": 15600.0,
        "ticket_promedio": 205.26,
        "boletos_online": 46,
        "subtotal_online": 8060.0,
        "boletos_taquilla": 30,
        "subtotal_taquilla": 7540.0
      },
      "Palco Plata 1ra": {
        "boletos": 48,
        "boletos_pagados": 48,
        "boletos_cortesias": 0,
        "boletos_cortesias_online": 0,
        "boletos_cortesias_taquilla": 0,
        "boletos_promocion": 0,
        "boletos_promocion_online": 0,
        "boletos_promocion_taquilla": 0,
        "subtotal": 12000.0,
        "ticket_promedio": 250.0,
        "boletos_online": 32,
        "subtotal_online": 7600.0,
        "boletos_taquilla": 16,
        "subtotal_taquilla": 4400.0
      },
      "Palco Plata 3ra": {
        "boletos": 42,
        "boletos_pagados": 42,
        "boletos_cortesias": 0,
        "boletos_cortesias_online": 0,
        "boletos_cortesias_taquilla": 0,
        "boletos_promocion": 0,
        "boletos_promocion_online": 0,
        "boletos_promocion_taquilla": 0,
        "subtotal": 21600.0,
        "ticket_promedio": 514.29,
        "boletos_online": 42,
        "subtotal_online": 21600.0,
        "boletos_taquilla": 0,
        "subtotal_taquilla": 0.0
      },
      "Palco Platino": {
        "boletos": 6,
        "boletos_pagados": 0,
        "boletos_cortesias": 6,
        "boletos_cortesias_online": 0,
        "boletos_cortesias_taquilla": 6,
        "boletos_promocion": 0,
        "boletos_promocion_online": 0,
        "boletos_promocion_taquilla": 0,
        "subtotal": 0.0,
        "ticket_promedio": 0,
        "boletos_online": 0,
        "subtotal_online": 0.0,
        "boletos_taquilla": 6,
        "subtotal_taquilla": 0.0
      }
    }
  },
  "Charros": {
    "subtotal": 1602298.0,
    "subtotal_online": 1428384.0,
    "subtotal_taquilla": 173914.0,
    "subtotal_paquete": 0.0,
    "subtotal_no_paquete": 1602298.0,
    "boletos": 9197,
    "boletos_online": 7364,
    "boletos_taquilla": 1833,
    "boletos_cortesias": 793,
    "boletos_cortesias_online": 0,
    "boletos_cortesias_taquilla": 793,
    "boletos_promocion": 673,
    "boletos_promocion_online": 622,
    "boletos_promocion_taquilla": 51,
    "cortesias_por_persona": [
      {
        "persona": "Mirza Valdez",
        "total": 490,
        "online": 0,
        "taquilla": 490
      },
      {
        "persona": "Rosaana",
        "total": 302,
        "online": 0,
        "taquilla": 302
      },
      {
        "persona": "Esmeralda Ruvalcaba",
        "total": 1,
        "online": 0,
        "taquilla": 1
      }
    ],
    "promocion_por_persona": [
      {
        "persona": "Venta en línea",
        "total": 622,
        "online": 622,
        "taquilla": 0
      },
      {
        "persona": "Estrella Magallanes",
        "total": 23,
        "online": 0,
        "taquilla": 23
      },
      {
        "persona": "Fabio Charros",
        "total": 11,
        "online": 0,
        "taquilla": 11
      },
      {
        "persona": "Rosaana",
        "total": 6,
        "online": 0,
        "taquilla": 6
      },
      {
        "persona": "Esmeralda Ruvalcaba",
        "total": 5,
        "online": 0,
        "taquilla": 5
      },
      {
        "persona": "Emiliano Negrete",
        "total": 3,
        "online": 0,
        "taquilla": 3
      },
      {
        "persona": "Diana Ramos",
        "total": 3,
        "online": 0,
        "taquilla": 3
      }
    ],
    "ordenes": 2529,
    "ordenes_online": 2245,
    "ordenes_taquilla": 284,
    "events": [
      "Juego Inaugural: Acereros vs Charros"
    ],
    "has_paquete": false,
    "first_date": "29/03/2026",
    "last_date": "16/04/2026",
    "duration_days": 18,
    "daily": [
      {
        "date": "2026-03-29",
        "subtotal": 163965.0,
        "boletos": 722
      },
      {
        "date": "2026-03-30",
        "subtotal": 109620.0,
        "boletos": 488
      },
      {
        "date": "2026-03-31",
        "subtotal": 195195.0,
        "boletos": 1016
      },
      {
        "date": "2026-04-01",
        "subtotal": 98475.0,
        "boletos": 587
      },
      {
        "date": "2026-04-02",
        "subtotal": 83535.0,
        "boletos": 335
      },
      {
        "date": "2026-04-03",
        "subtotal": 51990.0,
        "boletos": 257
      },
      {
        "date": "2026-04-04",
        "subtotal": 50460.0,
        "boletos": 255
      },
      {
        "date": "2026-04-05",
        "subtotal": 39690.0,
        "boletos": 216
      },
      {
        "date": "2026-04-06",
        "subtotal": 57630.0,
        "boletos": 253
      },
      {
        "date": "2026-04-07",
        "subtotal": 50160.0,
        "boletos": 254
      },
      {
        "date": "2026-04-08",
        "subtotal": 46350.0,
        "boletos": 243
      },
      {
        "date": "2026-04-09",
        "subtotal": 70485.0,
        "boletos": 422
      },
      {
        "date": "2026-04-10",
        "subtotal": 68835.0,
        "boletos": 421
      },
      {
        "date": "2026-04-11",
        "subtotal": 40860.0,
        "boletos": 257
      },
      {
        "date": "2026-04-12",
        "subtotal": 41340.0,
        "boletos": 248
      },
      {
        "date": "2026-04-13",
        "subtotal": 97530.0,
        "boletos": 605
      },
      {
        "date": "2026-04-14",
        "subtotal": 119994.0,
        "boletos": 798
      },
      {
        "date": "2026-04-15",
        "subtotal": 150790.0,
        "boletos": 1344
      },
      {
        "date": "2026-04-16",
        "subtotal": 65394.0,
        "boletos": 476
      }
    ],
    "zonas": {
      "Bleachers": {
        "boletos": 127,
        "boletos_pagados": 127,
        "boletos_cortesias": 0,
        "boletos_cortesias_online": 0,
        "boletos_cortesias_taquilla": 0,
        "boletos_promocion": 0,
        "boletos_promocion_online": 0,
        "boletos_promocion_taquilla": 0,
        "subtotal": 19050.0,
        "ticket_promedio": 150.0,
        "boletos_online": 127,
        "subtotal_online": 19050.0,
        "boletos_taquilla": 0,
        "subtotal_taquilla": 0.0
      },
      "Butaca Preferente Primera Base": {
        "boletos": 84,
        "boletos_pagados": 68,
        "boletos_cortesias": 0,
        "boletos_cortesias_online": 0,
        "boletos_cortesias_taquilla": 0,
        "boletos_promocion": 16,
        "boletos_promocion_online": 14,
        "boletos_promocion_taquilla": 2,
        "subtotal": 20400.0,
        "ticket_promedio": 242.86,
        "boletos_online": 76,
        "subtotal_online": 18600.0,
        "boletos_taquilla": 8,
        "subtotal_taquilla": 1800.0
      },
      "Butaca Preferente Tercera Base": {
        "boletos": 160,
        "boletos_pagados": 125,
        "boletos_cortesias": 0,
        "boletos_cortesias_online": 0,
        "boletos_cortesias_taquilla": 0,
        "boletos_promocion": 35,
        "boletos_promocion_online": 31,
        "boletos_promocion_taquilla": 4,
        "subtotal": 37500.0,
        "ticket_promedio": 234.38,
        "boletos_online": 142,
        "subtotal_online": 33300.0,
        "boletos_taquilla": 18,
        "subtotal_taquilla": 4200.0
      },
      "Gourmet": {
        "boletos": 368,
        "boletos_pagados": 368,
        "boletos_cortesias": 0,
        "boletos_cortesias_online": 0,
        "boletos_cortesias_taquilla": 0,
        "boletos_promocion": 0,
        "boletos_promocion_online": 0,
        "boletos_promocion_taquilla": 0,
        "subtotal": 39600.0,
        "ticket_promedio": 107.61,
        "boletos_online": 0,
        "subtotal_online": 0.0,
        "boletos_taquilla": 368,
        "subtotal_taquilla": 39600.0
      },
      "Lateral Alta Primera Base": {
        "boletos": 606,
        "boletos_pagados": 350,
        "boletos_cortesias": 256,
        "boletos_cortesias_online": 0,
        "boletos_cortesias_taquilla": 256,
        "boletos_promocion": 0,
        "boletos_promocion_online": 0,
        "boletos_promocion_taquilla": 0,
        "subtotal": 52500.0,
        "ticket_promedio": 150.0,
        "boletos_online": 334,
        "subtotal_online": 50100.0,
        "boletos_taquilla": 272,
        "subtotal_taquilla": 2400.0
      },
      "Lateral Preferente Alta": {
        "boletos": 479,
        "boletos_pagados": 458,
        "boletos_cortesias": 21,
        "boletos_cortesias_online": 0,
        "boletos_cortesias_taquilla": 21,
        "boletos_promocion": 0,
        "boletos_promocion_online": 0,
        "boletos_promocion_taquilla": 0,
        "subtotal": 62470.0,
        "ticket_promedio": 136.4,
        "boletos_online": 383,
        "subtotal_online": 57450.0,
        "boletos_taquilla": 96,
        "subtotal_taquilla": 5020.0
      },
      "Lateral Preferente Alta Tercera Base": {
        "boletos": 157,
        "boletos_pagados": 137,
        "boletos_cortesias": 20,
        "boletos_cortesias_online": 0,
        "boletos_cortesias_taquilla": 20,
        "boletos_promocion": 0,
        "boletos_promocion_online": 0,
        "boletos_promocion_taquilla": 0,
        "subtotal": 20550.0,
        "ticket_promedio": 150.0,
        "boletos_online": 137,
        "subtotal_online": 20550.0,
        "boletos_taquilla": 20,
        "subtotal_taquilla": 0.0
      },
      "Lateral Preferente Primera Base": {
        "boletos": 241,
        "boletos_pagados": 89,
        "boletos_cortesias": 129,
        "boletos_cortesias_online": 0,
        "boletos_cortesias_taquilla": 129,
        "boletos_promocion": 23,
        "boletos_promocion_online": 23,
        "boletos_promocion_taquilla": 0,
        "subtotal": 20025.0,
        "ticket_promedio": 178.79,
        "boletos_online": 112,
        "subtotal_online": 20025.0,
        "boletos_taquilla": 129,
        "subtotal_taquilla": 0.0
      },
      "Lateral Preferente Tercera Base": {
        "boletos": 200,
        "boletos_pagados": 75,
        "boletos_cortesias": 104,
        "boletos_cortesias_online": 0,
        "boletos_cortesias_taquilla": 104,
        "boletos_promocion": 21,
        "boletos_promocion_online": 21,
        "boletos_promocion_taquilla": 0,
        "subtotal": 16875.0,
        "ticket_promedio": 175.78,
        "boletos_online": 96,
        "subtotal_online": 16875.0,
        "boletos_taquilla": 104,
        "subtotal_taquilla": 0.0
      },
      "Lateral Primera Base": {
        "boletos": 1031,
        "boletos_pagados": 870,
        "boletos_cortesias": 77,
        "boletos_cortesias_online": 0,
        "boletos_cortesias_taquilla": 77,
        "boletos_promocion": 84,
        "boletos_promocion_online": 79,
        "boletos_promocion_taquilla": 5,
        "subtotal": 140694.0,
        "ticket_promedio": 147.48,
        "boletos_online": 898,
        "subtotal_online": 132564.0,
        "boletos_taquilla": 133,
        "subtotal_taquilla": 8130.0
      },
      "Lateral Tercera Base": {
        "boletos": 1015,
        "boletos_pagados": 907,
        "boletos_cortesias": 65,
        "boletos_cortesias_online": 0,
        "boletos_cortesias_taquilla": 65,
        "boletos_promocion": 43,
        "boletos_promocion_online": 42,
        "boletos_promocion_taquilla": 1,
        "subtotal": 146850.0,
        "ticket_promedio": 154.58,
        "boletos_online": 907,
        "subtotal_online": 139980.0,
        "boletos_taquilla": 108,
        "subtotal_taquilla": 6870.0
      },
      "Planta Alta Central": {
        "boletos": 1091,
        "boletos_pagados": 993,
        "boletos_cortesias": 12,
        "boletos_cortesias_online": 0,
        "boletos_cortesias_taquilla": 12,
        "boletos_promocion": 86,
        "boletos_promocion_online": 79,
        "boletos_promocion_taquilla": 7,
        "subtotal": 178578.0,
        "ticket_promedio": 165.5,
        "boletos_online": 947,
        "subtotal_online": 156240.0,
        "boletos_taquilla": 144,
        "subtotal_taquilla": 22338.0
      },
      "Planta Alta Lateral Primera Base": {
        "boletos": 904,
        "boletos_pagados": 847,
        "boletos_cortesias": 0,
        "boletos_cortesias_online": 0,
        "boletos_cortesias_taquilla": 0,
        "boletos_promocion": 57,
        "boletos_promocion_online": 54,
        "boletos_promocion_taquilla": 3,
        "subtotal": 126870.0,
        "ticket_promedio": 140.34,
        "boletos_online": 827,
        "subtotal_online": 115950.0,
        "boletos_taquilla": 77,
        "subtotal_taquilla": 10920.0
      },
      "Planta Alta Lateral Tercera Base": {
        "boletos": 854,
        "boletos_pagados": 829,
        "boletos_cortesias": 0,
        "boletos_cortesias_online": 0,
        "boletos_cortesias_taquilla": 0,
        "boletos_promocion": 25,
        "boletos_promocion_online": 23,
        "boletos_promocion_taquilla": 2,
        "subtotal": 124170.0,
        "ticket_promedio": 145.4,
        "boletos_online": 783,
        "subtotal_online": 114000.0,
        "boletos_taquilla": 71,
        "subtotal_taquilla": 10170.0
      },
      "Planta Baja": {
        "boletos": 843,
        "boletos_pagados": 690,
        "boletos_cortesias": 27,
        "boletos_cortesias_online": 0,
        "boletos_cortesias_taquilla": 27,
        "boletos_promocion": 126,
        "boletos_promocion_online": 112,
        "boletos_promocion_taquilla": 14,
        "subtotal": 206910.0,
        "ticket_promedio": 253.57,
        "boletos_online": 739,
        "subtotal_online": 188100.0,
        "boletos_taquilla": 104,
        "subtotal_taquilla": 18810.0
      },
      "Premier 1ra-3ra": {
        "boletos": 743,
        "boletos_pagados": 573,
        "boletos_cortesias": 58,
        "boletos_cortesias_online": 0,
        "boletos_cortesias_taquilla": 58,
        "boletos_promocion": 112,
        "boletos_promocion_online": 104,
        "boletos_promocion_taquilla": 8,
        "subtotal": 257850.0,
        "ticket_promedio": 376.42,
        "boletos_online": 648,
        "subtotal_online": 244800.0,
        "boletos_taquilla": 95,
        "subtotal_taquilla": 13050.0
      },
      "Premier Home": {
        "boletos": 276,
        "boletos_pagados": 225,
        "boletos_cortesias": 6,
        "boletos_cortesias_online": 0,
        "boletos_cortesias_taquilla": 6,
        "boletos_promocion": 45,
        "boletos_promocion_online": 40,
        "boletos_promocion_taquilla": 5,
        "subtotal": 131406.0,
        "ticket_promedio": 486.69,
        "boletos_online": 208,
        "subtotal_online": 100800.0,
        "boletos_taquilla": 68,
        "subtotal_taquilla": 30606.0
      },
      "SUITES": {
        "boletos": 18,
        "boletos_pagados": 0,
        "boletos_cortesias": 18,
        "boletos_cortesias_online": 0,
        "boletos_cortesias_taquilla": 18,
        "boletos_promocion": 0,
        "boletos_promocion_online": 0,
        "boletos_promocion_taquilla": 0,
        "subtotal": 0.0,
        "ticket_promedio": 0,
        "boletos_online": 0,
        "subtotal_online": 0.0,
        "boletos_taquilla": 18,
        "subtotal_taquilla": 0.0
      }
    }
  },
  "Dorados": {
    "subtotal": 397240.0,
    "subtotal_online": 336720.0,
    "subtotal_taquilla": 60520.0,
    "subtotal_paquete": 0.0,
    "subtotal_no_paquete": 397240.0,
    "boletos": 2821,
    "boletos_online": 2378,
    "boletos_taquilla": 443,
    "boletos_cortesias": 2,
    "boletos_cortesias_online": 0,
    "boletos_cortesias_taquilla": 2,
    "boletos_promocion": 101,
    "boletos_promocion_online": 101,
    "boletos_promocion_taquilla": 0,
    "cortesias_por_persona": [
      {
        "persona": "Monica Leon",
        "total": 2,
        "online": 0,
        "taquilla": 2
      }
    ],
    "promocion_por_persona": [
      {
        "persona": "Venta en línea",
        "total": 101,
        "online": 101,
        "taquilla": 0
      }
    ],
    "ordenes": 969,
    "ordenes_online": 832,
    "ordenes_taquilla": 137,
    "events": [
      "Juego Inaugural: Sultanes vs Dorados"
    ],
    "has_paquete": false,
    "first_date": "13/04/2026",
    "last_date": "16/04/2026",
    "duration_days": 3,
    "daily": [
      {
        "date": "2026-04-13",
        "subtotal": 3680.0,
        "boletos": 97
      },
      {
        "date": "2026-04-14",
        "subtotal": 203200.0,
        "boletos": 1266
      },
      {
        "date": "2026-04-15",
        "subtotal": 154140.0,
        "boletos": 1140
      },
      {
        "date": "2026-04-16",
        "subtotal": 36220.0,
        "boletos": 318
      }
    ],
    "zonas": {
      "Jardin Derecho": {
        "boletos": 392,
        "boletos_pagados": 384,
        "boletos_cortesias": 0,
        "boletos_cortesias_online": 0,
        "boletos_cortesias_taquilla": 0,
        "boletos_promocion": 8,
        "boletos_promocion_online": 8,
        "boletos_promocion_taquilla": 0,
        "subtotal": 38400.0,
        "ticket_promedio": 97.96,
        "boletos_online": 332,
        "subtotal_online": 32400.0,
        "boletos_taquilla": 60,
        "subtotal_taquilla": 6000.0
      },
      "Jardin Izquierdo": {
        "boletos": 112,
        "boletos_pagados": 112,
        "boletos_cortesias": 0,
        "boletos_cortesias_online": 0,
        "boletos_cortesias_taquilla": 0,
        "boletos_promocion": 0,
        "boletos_promocion_online": 0,
        "boletos_promocion_taquilla": 0,
        "subtotal": 11200.0,
        "ticket_promedio": 100.0,
        "boletos_online": 77,
        "subtotal_online": 7700.0,
        "boletos_taquilla": 35,
        "subtotal_taquilla": 3500.0
      },
      "Plata": {
        "boletos": 860,
        "boletos_pagados": 810,
        "boletos_cortesias": 0,
        "boletos_cortesias_online": 0,
        "boletos_cortesias_taquilla": 0,
        "boletos_promocion": 50,
        "boletos_promocion_online": 50,
        "boletos_promocion_taquilla": 0,
        "subtotal": 178200.0,
        "ticket_promedio": 207.21,
        "boletos_online": 765,
        "subtotal_online": 157300.0,
        "boletos_taquilla": 95,
        "subtotal_taquilla": 20900.0
      },
      "Preferente": {
        "boletos": 1457,
        "boletos_pagados": 1412,
        "boletos_cortesias": 2,
        "boletos_cortesias_online": 0,
        "boletos_cortesias_taquilla": 2,
        "boletos_promocion": 43,
        "boletos_promocion_online": 43,
        "boletos_promocion_taquilla": 0,
        "subtotal": 169440.0,
        "ticket_promedio": 116.45,
        "boletos_online": 1204,
        "subtotal_online": 139320.0,
        "boletos_taquilla": 253,
        "subtotal_taquilla": 30120.0
      }
    }
  },
  "Guerreros": {
    "subtotal": 116100.0,
    "subtotal_online": 116100.0,
    "subtotal_taquilla": 0.0,
    "subtotal_paquete": 0.0,
    "subtotal_no_paquete": 116100.0,
    "boletos": 362,
    "boletos_online": 258,
    "boletos_taquilla": 104,
    "boletos_cortesias": 104,
    "boletos_cortesias_online": 0,
    "boletos_cortesias_taquilla": 104,
    "boletos_promocion": 0,
    "boletos_promocion_online": 0,
    "boletos_promocion_taquilla": 0,
    "cortesias_por_persona": [
      {
        "persona": "Daniela Rios",
        "total": 104,
        "online": 0,
        "taquilla": 104
      }
    ],
    "promocion_por_persona": [],
    "ordenes": 63,
    "ordenes_online": 58,
    "ordenes_taquilla": 5,
    "events": [
      "Juego Inaugural: Conspiradores vs Guerreros",
      "Paquete Serie Inaugural: Conspiradores vs Guerreros"
    ],
    "has_paquete": true,
    "first_date": "13/04/2026",
    "last_date": "16/04/2026",
    "duration_days": 3,
    "daily": [
      {
        "date": "2026-04-13",
        "subtotal": 0.0,
        "boletos": 104
      },
      {
        "date": "2026-04-16",
        "subtotal": 116100.0,
        "boletos": 258
      }
    ],
    "zonas": {
      "Berma": {
        "boletos": 4,
        "boletos_pagados": 4,
        "boletos_cortesias": 0,
        "boletos_cortesias_online": 0,
        "boletos_cortesias_taquilla": 0,
        "boletos_promocion": 0,
        "boletos_promocion_online": 0,
        "boletos_promocion_taquilla": 0,
        "subtotal": 1200.0,
        "ticket_promedio": 300.0,
        "boletos_online": 4,
        "subtotal_online": 1200.0,
        "boletos_taquilla": 0,
        "subtotal_taquilla": 0.0
      },
      "Central": {
        "boletos": 242,
        "boletos_pagados": 138,
        "boletos_cortesias": 104,
        "boletos_cortesias_online": 0,
        "boletos_cortesias_taquilla": 104,
        "boletos_promocion": 0,
        "boletos_promocion_online": 0,
        "boletos_promocion_taquilla": 0,
        "subtotal": 69000.0,
        "ticket_promedio": 500.0,
        "boletos_online": 138,
        "subtotal_online": 69000.0,
        "boletos_taquilla": 104,
        "subtotal_taquilla": 0.0
      },
      "Dogout": {
        "boletos": 91,
        "boletos_pagados": 91,
        "boletos_cortesias": 0,
        "boletos_cortesias_online": 0,
        "boletos_cortesias_taquilla": 0,
        "boletos_promocion": 0,
        "boletos_promocion_online": 0,
        "boletos_promocion_taquilla": 0,
        "subtotal": 36400.0,
        "ticket_promedio": 400.0,
        "boletos_online": 91,
        "subtotal_online": 36400.0,
        "boletos_taquilla": 0,
        "subtotal_taquilla": 0.0
      },
      "Lateral": {
        "boletos": 25,
        "boletos_pagados": 25,
        "boletos_cortesias": 0,
        "boletos_cortesias_online": 0,
        "boletos_cortesias_taquilla": 0,
        "boletos_promocion": 0,
        "boletos_promocion_online": 0,
        "boletos_promocion_taquilla": 0,
        "subtotal": 9500.0,
        "ticket_promedio": 380.0,
        "boletos_online": 25,
        "subtotal_online": 9500.0,
        "boletos_taquilla": 0,
        "subtotal_taquilla": 0.0
      }
    }
  },
  "Rieleros": {
    "subtotal": 564200.0,
    "subtotal_online": 473750.0,
    "subtotal_taquilla": 90450.0,
    "subtotal_paquete": 0.0,
    "subtotal_no_paquete": 564200.0,
    "boletos": 3785,
    "boletos_online": 2614,
    "boletos_taquilla": 1171,
    "boletos_cortesias": 584,
    "boletos_cortesias_online": 0,
    "boletos_cortesias_taquilla": 584,
    "boletos_promocion": 200,
    "boletos_promocion_online": 200,
    "boletos_promocion_taquilla": 0,
    "cortesias_por_persona": [
      {
        "persona": "Edgar",
        "total": 548,
        "online": 0,
        "taquilla": 548
      },
      {
        "persona": "China",
        "total": 36,
        "online": 0,
        "taquilla": 36
      }
    ],
    "promocion_por_persona": [
      {
        "persona": "Venta en línea",
        "total": 200,
        "online": 200,
        "taquilla": 0
      }
    ],
    "ordenes": 1006,
    "ordenes_online": 829,
    "ordenes_taquilla": 177,
    "events": [
      "Juego Inaugural: Tecos vs Rieleros"
    ],
    "has_paquete": false,
    "first_date": "16/03/2026",
    "last_date": "16/04/2026",
    "duration_days": 31,
    "daily": [
      {
        "date": "2026-03-16",
        "subtotal": 2800.0,
        "boletos": 10
      },
      {
        "date": "2026-03-17",
        "subtotal": 2430.0,
        "boletos": 13
      },
      {
        "date": "2026-03-18",
        "subtotal": 3820.0,
        "boletos": 20
      },
      {
        "date": "2026-03-19",
        "subtotal": 1920.0,
        "boletos": 8
      },
      {
        "date": "2026-03-20",
        "subtotal": 16160.0,
        "boletos": 80
      },
      {
        "date": "2026-03-21",
        "subtotal": 3520.0,
        "boletos": 14
      },
      {
        "date": "2026-03-22",
        "subtotal": 2000.0,
        "boletos": 11
      },
      {
        "date": "2026-03-23",
        "subtotal": 4990.0,
        "boletos": 27
      },
      {
        "date": "2026-03-24",
        "subtotal": 5860.0,
        "boletos": 36
      },
      {
        "date": "2026-03-25",
        "subtotal": 2580.0,
        "boletos": 11
      },
      {
        "date": "2026-03-26",
        "subtotal": 7180.0,
        "boletos": 34
      },
      {
        "date": "2026-03-27",
        "subtotal": 8510.0,
        "boletos": 35
      },
      {
        "date": "2026-03-28",
        "subtotal": 5850.0,
        "boletos": 24
      },
      {
        "date": "2026-03-29",
        "subtotal": 17960.0,
        "boletos": 91
      },
      {
        "date": "2026-03-30",
        "subtotal": 7930.0,
        "boletos": 40
      },
      {
        "date": "2026-03-31",
        "subtotal": 9850.0,
        "boletos": 46
      },
      {
        "date": "2026-04-01",
        "subtotal": 10970.0,
        "boletos": 47
      },
      {
        "date": "2026-04-02",
        "subtotal": 6800.0,
        "boletos": 31
      },
      {
        "date": "2026-04-03",
        "subtotal": 7130.0,
        "boletos": 34
      },
      {
        "date": "2026-04-04",
        "subtotal": 13110.0,
        "boletos": 63
      },
      {
        "date": "2026-04-05",
        "subtotal": 7920.0,
        "boletos": 38
      },
      {
        "date": "2026-04-06",
        "subtotal": 25410.0,
        "boletos": 120
      },
      {
        "date": "2026-04-07",
        "subtotal": 13900.0,
        "boletos": 87
      },
      {
        "date": "2026-04-08",
        "subtotal": 27640.0,
        "boletos": 142
      },
      {
        "date": "2026-04-09",
        "subtotal": 32770.0,
        "boletos": 164
      },
      {
        "date": "2026-04-10",
        "subtotal": 46940.0,
        "boletos": 299
      },
      {
        "date": "2026-04-11",
        "subtotal": 58800.0,
        "boletos": 319
      },
      {
        "date": "2026-04-12",
        "subtotal": 25930.0,
        "boletos": 146
      },
      {
        "date": "2026-04-13",
        "subtotal": 57850.0,
        "boletos": 308
      },
      {
        "date": "2026-04-14",
        "subtotal": 52190.0,
        "boletos": 841
      },
      {
        "date": "2026-04-15",
        "subtotal": 51430.0,
        "boletos": 435
      },
      {
        "date": "2026-04-16",
        "subtotal": 22050.0,
        "boletos": 211
      }
    ],
    "zonas": {
      "Discapacitados": {
        "boletos": 3,
        "boletos_pagados": 3,
        "boletos_cortesias": 0,
        "boletos_cortesias_online": 0,
        "boletos_cortesias_taquilla": 0,
        "boletos_promocion": 0,
        "boletos_promocion_online": 0,
        "boletos_promocion_taquilla": 0,
        "subtotal": 150.0,
        "ticket_promedio": 50.0,
        "boletos_online": 1,
        "subtotal_online": 50.0,
        "boletos_taquilla": 2,
        "subtotal_taquilla": 100.0
      },
      "Home Oro": {
        "boletos": 56,
        "boletos_pagados": 54,
        "boletos_cortesias": 2,
        "boletos_cortesias_online": 0,
        "boletos_cortesias_taquilla": 2,
        "boletos_promocion": 0,
        "boletos_promocion_online": 0,
        "boletos_promocion_taquilla": 0,
        "subtotal": 18360.0,
        "ticket_promedio": 340.0,
        "boletos_online": 54,
        "subtotal_online": 18360.0,
        "boletos_taquilla": 2,
        "subtotal_taquilla": 0.0
      },
      "Palco Plus Derecho": {
        "boletos": 140,
        "boletos_pagados": 140,
        "boletos_cortesias": 0,
        "boletos_cortesias_online": 0,
        "boletos_cortesias_taquilla": 0,
        "boletos_promocion": 0,
        "boletos_promocion_online": 0,
        "boletos_promocion_taquilla": 0,
        "subtotal": 30800.0,
        "ticket_promedio": 220.0,
        "boletos_online": 130,
        "subtotal_online": 28600.0,
        "boletos_taquilla": 10,
        "subtotal_taquilla": 2200.0
      },
      "Palco Plus izquierdo": {
        "boletos": 127,
        "boletos_pagados": 127,
        "boletos_cortesias": 0,
        "boletos_cortesias_online": 0,
        "boletos_cortesias_taquilla": 0,
        "boletos_promocion": 0,
        "boletos_promocion_online": 0,
        "boletos_promocion_taquilla": 0,
        "subtotal": 27940.0,
        "ticket_promedio": 220.0,
        "boletos_online": 110,
        "subtotal_online": 24200.0,
        "boletos_taquilla": 17,
        "subtotal_taquilla": 3740.0
      },
      "Preferente Derecho": {
        "boletos": 710,
        "boletos_pagados": 588,
        "boletos_cortesias": 6,
        "boletos_cortesias_online": 0,
        "boletos_cortesias_taquilla": 6,
        "boletos_promocion": 116,
        "boletos_promocion_online": 116,
        "boletos_promocion_taquilla": 0,
        "subtotal": 64680.0,
        "ticket_promedio": 91.88,
        "boletos_online": 480,
        "subtotal_online": 40040.0,
        "boletos_taquilla": 230,
        "subtotal_taquilla": 24640.0
      },
      "Preferente Izquierdo": {
        "boletos": 676,
        "boletos_pagados": 210,
        "boletos_cortesias": 404,
        "boletos_cortesias_online": 0,
        "boletos_cortesias_taquilla": 404,
        "boletos_promocion": 62,
        "boletos_promocion_online": 62,
        "boletos_promocion_taquilla": 0,
        "subtotal": 23100.0,
        "ticket_promedio": 84.93,
        "boletos_online": 214,
        "subtotal_online": 16720.0,
        "boletos_taquilla": 462,
        "subtotal_taquilla": 6380.0
      },
      "Suite": {
        "boletos": 12,
        "boletos_pagados": 0,
        "boletos_cortesias": 12,
        "boletos_cortesias_online": 0,
        "boletos_cortesias_taquilla": 12,
        "boletos_promocion": 0,
        "boletos_promocion_online": 0,
        "boletos_promocion_taquilla": 0,
        "subtotal": 0.0,
        "ticket_promedio": 0,
        "boletos_online": 0,
        "subtotal_online": 0.0,
        "boletos_taquilla": 12,
        "subtotal_taquilla": 0.0
      },
      "Tablitas": {
        "boletos": 78,
        "boletos_pagados": 56,
        "boletos_cortesias": 0,
        "boletos_cortesias_online": 0,
        "boletos_cortesias_taquilla": 0,
        "boletos_promocion": 22,
        "boletos_promocion_online": 22,
        "boletos_promocion_taquilla": 0,
        "subtotal": 4480.0,
        "ticket_promedio": 57.44,
        "boletos_online": 55,
        "subtotal_online": 2640.0,
        "boletos_taquilla": 23,
        "subtotal_taquilla": 1840.0
      },
      "Terraza 1er": {
        "boletos": 196,
        "boletos_pagados": 192,
        "boletos_cortesias": 4,
        "boletos_cortesias_online": 0,
        "boletos_cortesias_taquilla": 4,
        "boletos_promocion": 0,
        "boletos_promocion_online": 0,
        "boletos_promocion_taquilla": 0,
        "subtotal": 19200.0,
        "ticket_promedio": 100.0,
        "boletos_online": 146,
        "subtotal_online": 14600.0,
        "boletos_taquilla": 50,
        "subtotal_taquilla": 4600.0
      },
      "Terraza 3ra": {
        "boletos": 200,
        "boletos_pagados": 200,
        "boletos_cortesias": 0,
        "boletos_cortesias_online": 0,
        "boletos_cortesias_taquilla": 0,
        "boletos_promocion": 0,
        "boletos_promocion_online": 0,
        "boletos_promocion_taquilla": 0,
        "subtotal": 20000.0,
        "ticket_promedio": 100.0,
        "boletos_online": 178,
        "subtotal_online": 17800.0,
        "boletos_taquilla": 22,
        "subtotal_taquilla": 2200.0
      },
      "Zona Plata": {
        "boletos": 536,
        "boletos_pagados": 496,
        "boletos_cortesias": 40,
        "boletos_cortesias_online": 0,
        "boletos_cortesias_taquilla": 40,
        "boletos_promocion": 0,
        "boletos_promocion_online": 0,
        "boletos_promocion_taquilla": 0,
        "subtotal": 119040.0,
        "ticket_promedio": 240.0,
        "boletos_online": 466,
        "subtotal_online": 111840.0,
        "boletos_taquilla": 70,
        "subtotal_taquilla": 7200.0
      },
      "Zona Rielera 1era.": {
        "boletos": 334,
        "boletos_pagados": 294,
        "boletos_cortesias": 40,
        "boletos_cortesias_online": 0,
        "boletos_cortesias_taquilla": 40,
        "boletos_promocion": 0,
        "boletos_promocion_online": 0,
        "boletos_promocion_taquilla": 0,
        "subtotal": 67620.0,
        "ticket_promedio": 230.0,
        "boletos_online": 240,
        "subtotal_online": 55200.0,
        "boletos_taquilla": 94,
        "subtotal_taquilla": 12420.0
      },
      "Zona Rielera 3ra.": {
        "boletos": 283,
        "boletos_pagados": 213,
        "boletos_cortesias": 70,
        "boletos_cortesias_online": 0,
        "boletos_cortesias_taquilla": 70,
        "boletos_promocion": 0,
        "boletos_promocion_online": 0,
        "boletos_promocion_taquilla": 0,
        "subtotal": 48990.0,
        "ticket_promedio": 230.0,
        "boletos_online": 150,
        "subtotal_online": 34500.0,
        "boletos_taquilla": 133,
        "subtotal_taquilla": 14490.0
      },
      "Zona VIP": {
        "boletos": 434,
        "boletos_pagados": 428,
        "boletos_cortesias": 6,
        "boletos_cortesias_online": 0,
        "boletos_cortesias_taquilla": 6,
        "boletos_promocion": 0,
        "boletos_promocion_online": 0,
        "boletos_promocion_taquilla": 0,
        "subtotal": 119840.0,
        "ticket_promedio": 280.0,
        "boletos_online": 390,
        "subtotal_online": 109200.0,
        "boletos_taquilla": 44,
        "subtotal_taquilla": 10640.0
      }
    }
  },
  "Saraperos": {
    "subtotal": 1875200.0,
    "subtotal_online": 1250550.0,
    "subtotal_taquilla": 624650.0,
    "subtotal_paquete": 0.0,
    "subtotal_no_paquete": 1875200.0,
    "boletos": 5319,
    "boletos_online": 3477,
    "boletos_taquilla": 1842,
    "boletos_cortesias": 349,
    "boletos_cortesias_online": 0,
    "boletos_cortesias_taquilla": 349,
    "boletos_promocion": 0,
    "boletos_promocion_online": 0,
    "boletos_promocion_taquilla": 0,
    "cortesias_por_persona": [
      {
        "persona": "Martin Rivera",
        "total": 305,
        "online": 0,
        "taquilla": 305
      },
      {
        "persona": "Eveling Morales",
        "total": 44,
        "online": 0,
        "taquilla": 44
      }
    ],
    "promocion_por_persona": [],
    "ordenes": 1729,
    "ordenes_online": 1465,
    "ordenes_taquilla": 264,
    "events": [
      "Juego Inaugural: Toros vs Saraperos"
    ],
    "has_paquete": false,
    "first_date": "11/04/2026",
    "last_date": "16/04/2026",
    "duration_days": 5,
    "daily": [
      {
        "date": "2026-04-11",
        "subtotal": 15000.0,
        "boletos": 16
      },
      {
        "date": "2026-04-13",
        "subtotal": 0.0,
        "boletos": 226
      },
      {
        "date": "2026-04-14",
        "subtotal": 976200.0,
        "boletos": 2326
      },
      {
        "date": "2026-04-15",
        "subtotal": 840850.0,
        "boletos": 2626
      },
      {
        "date": "2026-04-16",
        "subtotal": 43150.0,
        "boletos": 125
      }
    ],
    "zonas": {
      "Area Contenedores": {
        "boletos": 130,
        "boletos_pagados": 106,
        "boletos_cortesias": 24,
        "boletos_cortesias_online": 0,
        "boletos_cortesias_taquilla": 24,
        "boletos_promocion": 0,
        "boletos_promocion_online": 0,
        "boletos_promocion_taquilla": 0,
        "subtotal": 60000.0,
        "ticket_promedio": 566.04,
        "boletos_online": 73,
        "subtotal_online": 36500.0,
        "boletos_taquilla": 57,
        "subtotal_taquilla": 23500.0
      },
      "Butaca Central B": {
        "boletos": 1910,
        "boletos_pagados": 1810,
        "boletos_cortesias": 100,
        "boletos_cortesias_online": 0,
        "boletos_cortesias_taquilla": 100,
        "boletos_promocion": 0,
        "boletos_promocion_online": 0,
        "boletos_promocion_taquilla": 0,
        "subtotal": 905000.0,
        "ticket_promedio": 500.0,
        "boletos_online": 1117,
        "subtotal_online": 558500.0,
        "boletos_taquilla": 793,
        "subtotal_taquilla": 346500.0
      },
      "Butaca Lateral A": {
        "boletos": 1066,
        "boletos_pagados": 936,
        "boletos_cortesias": 130,
        "boletos_cortesias_online": 0,
        "boletos_cortesias_taquilla": 130,
        "boletos_promocion": 0,
        "boletos_promocion_online": 0,
        "boletos_promocion_taquilla": 0,
        "subtotal": 327600.0,
        "ticket_promedio": 350.0,
        "boletos_online": 543,
        "subtotal_online": 190050.0,
        "boletos_taquilla": 523,
        "subtotal_taquilla": 137550.0
      },
      "Butaca Lateral C": {
        "boletos": 1136,
        "boletos_pagados": 1060,
        "boletos_cortesias": 76,
        "boletos_cortesias_online": 0,
        "boletos_cortesias_taquilla": 76,
        "boletos_promocion": 0,
        "boletos_promocion_online": 0,
        "boletos_promocion_taquilla": 0,
        "subtotal": 371000.0,
        "ticket_promedio": 350.0,
        "boletos_online": 778,
        "subtotal_online": 272300.0,
        "boletos_taquilla": 358,
        "subtotal_taquilla": 98700.0
      },
      "General-Gradas": {
        "boletos": 1058,
        "boletos_pagados": 1058,
        "boletos_cortesias": 0,
        "boletos_cortesias_online": 0,
        "boletos_cortesias_taquilla": 0,
        "boletos_promocion": 0,
        "boletos_promocion_online": 0,
        "boletos_promocion_taquilla": 0,
        "subtotal": 211600.0,
        "ticket_promedio": 200.0,
        "boletos_online": 966,
        "subtotal_online": 193200.0,
        "boletos_taquilla": 92,
        "subtotal_taquilla": 18400.0
      },
      "Palco Presi": {
        "boletos": 19,
        "boletos_pagados": 0,
        "boletos_cortesias": 19,
        "boletos_cortesias_online": 0,
        "boletos_cortesias_taquilla": 19,
        "boletos_promocion": 0,
        "boletos_promocion_online": 0,
        "boletos_promocion_taquilla": 0,
        "subtotal": 0.0,
        "ticket_promedio": 0,
        "boletos_online": 0,
        "subtotal_online": 0.0,
        "boletos_taquilla": 19,
        "subtotal_taquilla": 0.0
      }
    }
  },
  "Sultanes": {
    "subtotal": 2303523.9,
    "subtotal_online": 1857163.0,
    "subtotal_taquilla": 446360.9,
    "subtotal_paquete": 0.0,
    "subtotal_no_paquete": 2303523.9,
    "boletos": 14900,
    "boletos_online": 11267,
    "boletos_taquilla": 3633,
    "boletos_cortesias": 349,
    "boletos_cortesias_online": 0,
    "boletos_cortesias_taquilla": 349,
    "boletos_promocion": 1875,
    "boletos_promocion_online": 0,
    "boletos_promocion_taquilla": 1875,
    "cortesias_por_persona": [
      {
        "persona": "Supervisor 3",
        "total": 311,
        "online": 0,
        "taquilla": 311
      },
      {
        "persona": "Gabriela Puente",
        "total": 30,
        "online": 0,
        "taquilla": 30
      },
      {
        "persona": "Daniela Peña Martínez",
        "total": 4,
        "online": 0,
        "taquilla": 4
      },
      {
        "persona": "Supervisor 2",
        "total": 4,
        "online": 0,
        "taquilla": 4
      }
    ],
    "promocion_por_persona": [
      {
        "persona": "Eduardo Garza",
        "total": 1666,
        "online": 0,
        "taquilla": 1666
      },
      {
        "persona": "Daniela Peña Martínez",
        "total": 97,
        "online": 0,
        "taquilla": 97
      },
      {
        "persona": "Gabriela Puente",
        "total": 90,
        "online": 0,
        "taquilla": 90
      },
      {
        "persona": "Supervisor 3",
        "total": 22,
        "online": 0,
        "taquilla": 22
      }
    ],
    "ordenes": 4196,
    "ordenes_online": 3802,
    "ordenes_taquilla": 394,
    "events": [
      "Juego Inaugural: Durango vs Sultanes"
    ],
    "has_paquete": false,
    "first_date": "12/03/2026",
    "last_date": "16/04/2026",
    "duration_days": 35,
    "daily": [
      {
        "date": "2026-03-12",
        "subtotal": 87367.0,
        "boletos": 541
      },
      {
        "date": "2026-03-13",
        "subtotal": 41160.0,
        "boletos": 253
      },
      {
        "date": "2026-03-14",
        "subtotal": 51296.0,
        "boletos": 320
      },
      {
        "date": "2026-03-15",
        "subtotal": 25230.0,
        "boletos": 121
      },
      {
        "date": "2026-03-16",
        "subtotal": 9940.0,
        "boletos": 47
      },
      {
        "date": "2026-03-17",
        "subtotal": 57100.2,
        "boletos": 137
      },
      {
        "date": "2026-03-18",
        "subtotal": 29140.0,
        "boletos": 81
      },
      {
        "date": "2026-03-19",
        "subtotal": 68900.0,
        "boletos": 321
      },
      {
        "date": "2026-03-20",
        "subtotal": 43430.0,
        "boletos": 207
      },
      {
        "date": "2026-03-21",
        "subtotal": 25400.0,
        "boletos": 121
      },
      {
        "date": "2026-03-22",
        "subtotal": 30240.0,
        "boletos": 145
      },
      {
        "date": "2026-03-23",
        "subtotal": 36220.0,
        "boletos": 173
      },
      {
        "date": "2026-03-24",
        "subtotal": 31930.0,
        "boletos": 146
      },
      {
        "date": "2026-03-25",
        "subtotal": 25280.0,
        "boletos": 119
      },
      {
        "date": "2026-03-26",
        "subtotal": 27810.0,
        "boletos": 132
      },
      {
        "date": "2026-03-27",
        "subtotal": 53620.0,
        "boletos": 249
      },
      {
        "date": "2026-03-28",
        "subtotal": 30260.0,
        "boletos": 144
      },
      {
        "date": "2026-03-29",
        "subtotal": 18890.0,
        "boletos": 92
      },
      {
        "date": "2026-03-30",
        "subtotal": 26170.0,
        "boletos": 123
      },
      {
        "date": "2026-03-31",
        "subtotal": 42280.0,
        "boletos": 147
      },
      {
        "date": "2026-04-01",
        "subtotal": 27640.0,
        "boletos": 160
      },
      {
        "date": "2026-04-02",
        "subtotal": 37620.1,
        "boletos": 115
      },
      {
        "date": "2026-04-03",
        "subtotal": 34870.0,
        "boletos": 1362
      },
      {
        "date": "2026-04-04",
        "subtotal": 38650.0,
        "boletos": 194
      },
      {
        "date": "2026-04-05",
        "subtotal": 20700.0,
        "boletos": 117
      },
      {
        "date": "2026-04-06",
        "subtotal": 160750.4,
        "boletos": 923
      },
      {
        "date": "2026-04-07",
        "subtotal": 103300.0,
        "boletos": 578
      },
      {
        "date": "2026-04-08",
        "subtotal": 85480.0,
        "boletos": 470
      },
      {
        "date": "2026-04-09",
        "subtotal": 81130.0,
        "boletos": 508
      },
      {
        "date": "2026-04-10",
        "subtotal": 59560.0,
        "boletos": 410
      },
      {
        "date": "2026-04-11",
        "subtotal": 40440.0,
        "boletos": 309
      },
      {
        "date": "2026-04-12",
        "subtotal": 63620.0,
        "boletos": 498
      },
      {
        "date": "2026-04-13",
        "subtotal": 231340.2,
        "boletos": 1458
      },
      {
        "date": "2026-04-14",
        "subtotal": 235900.0,
        "boletos": 1644
      },
      {
        "date": "2026-04-15",
        "subtotal": 221140.0,
        "boletos": 1678
      },
      {
        "date": "2026-04-16",
        "subtotal": 99720.0,
        "boletos": 857
      }
    ],
    "zonas": {
      "Bleachers": {
        "boletos": 3274,
        "boletos_pagados": 3263,
        "boletos_cortesias": 0,
        "boletos_cortesias_online": 0,
        "boletos_cortesias_taquilla": 0,
        "boletos_promocion": 11,
        "boletos_promocion_online": 0,
        "boletos_promocion_taquilla": 11,
        "subtotal": 486644.0,
        "ticket_promedio": 148.64,
        "boletos_online": 2959,
        "subtotal_online": 440324.0,
        "boletos_taquilla": 315,
        "subtotal_taquilla": 46320.0
      },
      "PCD": {
        "boletos": 2,
        "boletos_pagados": 2,
        "boletos_cortesias": 0,
        "boletos_cortesias_online": 0,
        "boletos_cortesias_taquilla": 0,
        "boletos_promocion": 0,
        "boletos_promocion_online": 0,
        "boletos_promocion_taquilla": 0,
        "subtotal": 440.0,
        "ticket_promedio": 220.0,
        "boletos_online": 2,
        "subtotal_online": 440.0,
        "boletos_taquilla": 0,
        "subtotal_taquilla": 0.0
      },
      "Palco Azul": {
        "boletos": 202,
        "boletos_pagados": 132,
        "boletos_cortesias": 0,
        "boletos_cortesias_online": 0,
        "boletos_cortesias_taquilla": 0,
        "boletos_promocion": 70,
        "boletos_promocion_online": 0,
        "boletos_promocion_taquilla": 70,
        "subtotal": 36420.0,
        "ticket_promedio": 180.3,
        "boletos_online": 126,
        "subtotal_online": 34820.0,
        "boletos_taquilla": 76,
        "subtotal_taquilla": 1600.0
      },
      "Palco Rojo": {
        "boletos": 231,
        "boletos_pagados": 121,
        "boletos_cortesias": 6,
        "boletos_cortesias_online": 0,
        "boletos_cortesias_taquilla": 6,
        "boletos_promocion": 104,
        "boletos_promocion_online": 0,
        "boletos_promocion_taquilla": 104,
        "subtotal": 30470.0,
        "ticket_promedio": 135.42,
        "boletos_online": 119,
        "subtotal_online": 29970.0,
        "boletos_taquilla": 112,
        "subtotal_taquilla": 500.0
      },
      "Parrilladas": {
        "boletos": 500,
        "boletos_pagados": 380,
        "boletos_cortesias": 30,
        "boletos_cortesias_online": 0,
        "boletos_cortesias_taquilla": 30,
        "boletos_promocion": 90,
        "boletos_promocion_online": 0,
        "boletos_promocion_taquilla": 90,
        "subtotal": 263000.9,
        "ticket_promedio": 559.58,
        "boletos_online": 0,
        "subtotal_online": 0.0,
        "boletos_taquilla": 500,
        "subtotal_taquilla": 263000.9
      },
      "Primer Nivel": {
        "boletos": 5110,
        "boletos_pagados": 3875,
        "boletos_cortesias": 128,
        "boletos_cortesias_online": 0,
        "boletos_cortesias_taquilla": 128,
        "boletos_promocion": 1107,
        "boletos_promocion_online": 0,
        "boletos_promocion_taquilla": 1107,
        "subtotal": 757444.0,
        "ticket_promedio": 152.04,
        "boletos_online": 3519,
        "subtotal_online": 687854.0,
        "boletos_taquilla": 1591,
        "subtotal_taquilla": 69590.0
      },
      "Segundo Nivel": {
        "boletos": 1919,
        "boletos_pagados": 1530,
        "boletos_cortesias": 160,
        "boletos_cortesias_online": 0,
        "boletos_cortesias_taquilla": 160,
        "boletos_promocion": 229,
        "boletos_promocion_online": 0,
        "boletos_promocion_taquilla": 229,
        "subtotal": 284905.0,
        "ticket_promedio": 161.97,
        "boletos_online": 1373,
        "subtotal_online": 255155.0,
        "boletos_taquilla": 546,
        "subtotal_taquilla": 29750.0
      },
      "Suites Primer Nivel": {
        "boletos": 36,
        "boletos_pagados": 12,
        "boletos_cortesias": 0,
        "boletos_cortesias_online": 0,
        "boletos_cortesias_taquilla": 0,
        "boletos_promocion": 24,
        "boletos_promocion_online": 0,
        "boletos_promocion_taquilla": 24,
        "subtotal": 12000.0,
        "ticket_promedio": 333.33,
        "boletos_online": 0,
        "subtotal_online": 0.0,
        "boletos_taquilla": 36,
        "subtotal_taquilla": 12000.0
      },
      "Suites Segundo Nivel": {
        "boletos": 109,
        "boletos_pagados": 0,
        "boletos_cortesias": 25,
        "boletos_cortesias_online": 0,
        "boletos_cortesias_taquilla": 25,
        "boletos_promocion": 84,
        "boletos_promocion_online": 0,
        "boletos_promocion_taquilla": 84,
        "subtotal": 0.0,
        "ticket_promedio": 0.0,
        "boletos_online": 0,
        "subtotal_online": 0.0,
        "boletos_taquilla": 109,
        "subtotal_taquilla": 0.0
      },
      "Tercer Nivel": {
        "boletos": 3517,
        "boletos_pagados": 3361,
        "boletos_cortesias": 0,
        "boletos_cortesias_online": 0,
        "boletos_cortesias_taquilla": 0,
        "boletos_promocion": 156,
        "boletos_promocion_online": 0,
        "boletos_promocion_taquilla": 156,
        "subtotal": 432200.0,
        "ticket_promedio": 122.89,
        "boletos_online": 3169,
        "subtotal_online": 408600.0,
        "boletos_taquilla": 348,
        "subtotal_taquilla": 23600.0
      }
    }
  },
  "Tecos": {
    "subtotal": 169220.0,
    "subtotal_online": 139030.0,
    "subtotal_taquilla": 30190.0,
    "subtotal_paquete": 0.0,
    "subtotal_no_paquete": 169220.0,
    "boletos": 433,
    "boletos_online": 346,
    "boletos_taquilla": 87,
    "boletos_cortesias": 0,
    "boletos_cortesias_online": 0,
    "boletos_cortesias_taquilla": 0,
    "boletos_promocion": 4,
    "boletos_promocion_online": 0,
    "boletos_promocion_taquilla": 4,
    "cortesias_por_persona": [],
    "promocion_por_persona": [
      {
        "persona": "Carlos Martinez.",
        "total": 4,
        "online": 0,
        "taquilla": 4
      }
    ],
    "ordenes": 158,
    "ordenes_online": 127,
    "ordenes_taquilla": 31,
    "events": [
      "Juego Inaugural: Charros vs Tecos"
    ],
    "has_paquete": false,
    "first_date": "14/04/2026",
    "last_date": "16/04/2026",
    "duration_days": 2,
    "daily": [
      {
        "date": "2026-04-14",
        "subtotal": 94120.0,
        "boletos": 234
      },
      {
        "date": "2026-04-15",
        "subtotal": 63480.0,
        "boletos": 170
      },
      {
        "date": "2026-04-16",
        "subtotal": 11620.0,
        "boletos": 29
      }
    ],
    "zonas": {
      "Butaca General": {
        "boletos": 164,
        "boletos_pagados": 164,
        "boletos_cortesias": 0,
        "boletos_cortesias_online": 0,
        "boletos_cortesias_taquilla": 0,
        "boletos_promocion": 0,
        "boletos_promocion_online": 0,
        "boletos_promocion_taquilla": 0,
        "subtotal": 62320.0,
        "ticket_promedio": 380.0,
        "boletos_online": 144,
        "subtotal_online": 54720.0,
        "boletos_taquilla": 20,
        "subtotal_taquilla": 7600.0
      },
      "Butaca Preferente": {
        "boletos": 203,
        "boletos_pagados": 199,
        "boletos_cortesias": 0,
        "boletos_cortesias_online": 0,
        "boletos_cortesias_taquilla": 0,
        "boletos_promocion": 4,
        "boletos_promocion_online": 0,
        "boletos_promocion_taquilla": 4,
        "subtotal": 85570.0,
        "ticket_promedio": 421.53,
        "boletos_online": 168,
        "subtotal_online": 72240.0,
        "boletos_taquilla": 35,
        "subtotal_taquilla": 13330.0
      },
      "Gradas": {
        "boletos": 47,
        "boletos_pagados": 47,
        "boletos_cortesias": 0,
        "boletos_cortesias_online": 0,
        "boletos_cortesias_taquilla": 0,
        "boletos_promocion": 0,
        "boletos_promocion_online": 0,
        "boletos_promocion_taquilla": 0,
        "subtotal": 13160.0,
        "ticket_promedio": 280.0,
        "boletos_online": 17,
        "subtotal_online": 4760.0,
        "boletos_taquilla": 30,
        "subtotal_taquilla": 8400.0
      },
      "Palcos 1ra": {
        "boletos": 8,
        "boletos_pagados": 8,
        "boletos_cortesias": 0,
        "boletos_cortesias_online": 0,
        "boletos_cortesias_taquilla": 0,
        "boletos_promocion": 0,
        "boletos_promocion_online": 0,
        "boletos_promocion_taquilla": 0,
        "subtotal": 3440.0,
        "ticket_promedio": 430.0,
        "boletos_online": 8,
        "subtotal_online": 3440.0,
        "boletos_taquilla": 0,
        "subtotal_taquilla": 0.0
      },
      "Palcos 3ra": {
        "boletos": 11,
        "boletos_pagados": 11,
        "boletos_cortesias": 0,
        "boletos_cortesias_online": 0,
        "boletos_cortesias_taquilla": 0,
        "boletos_promocion": 0,
        "boletos_promocion_online": 0,
        "boletos_promocion_taquilla": 0,
        "subtotal": 4730.0,
        "ticket_promedio": 430.0,
        "boletos_online": 9,
        "subtotal_online": 3870.0,
        "boletos_taquilla": 2,
        "subtotal_taquilla": 860.0
      }
    }
  },
  "Toros": {
    "subtotal": 4317567.0,
    "subtotal_online": 2455370.0,
    "subtotal_taquilla": 1862197.0,
    "subtotal_paquete": 4066970.0,
    "subtotal_no_paquete": 250597.0,
    "boletos": 7085,
    "boletos_online": 3416,
    "boletos_taquilla": 3669,
    "boletos_cortesias": 851,
    "boletos_cortesias_online": 0,
    "boletos_cortesias_taquilla": 851,
    "boletos_promocion": 29,
    "boletos_promocion_online": 1,
    "boletos_promocion_taquilla": 28,
    "cortesias_por_persona": [
      {
        "persona": "Karla Marquez",
        "total": 392,
        "online": 0,
        "taquilla": 392
      },
      {
        "persona": "Liliana Ancheyta",
        "total": 237,
        "online": 0,
        "taquilla": 237
      },
      {
        "persona": "Yerah Hernández",
        "total": 144,
        "online": 0,
        "taquilla": 144
      },
      {
        "persona": "Julio Carrazco",
        "total": 50,
        "online": 0,
        "taquilla": 50
      },
      {
        "persona": "Administrador Boletomóvil",
        "total": 10,
        "online": 0,
        "taquilla": 10
      },
      {
        "persona": "Yae García",
        "total": 9,
        "online": 0,
        "taquilla": 9
      },
      {
        "persona": "Ashlee Antonio",
        "total": 5,
        "online": 0,
        "taquilla": 5
      },
      {
        "persona": "Perla Rosangel",
        "total": 4,
        "online": 0,
        "taquilla": 4
      }
    ],
    "promocion_por_persona": [
      {
        "persona": "Julio Carrazco",
        "total": 21,
        "online": 0,
        "taquilla": 21
      },
      {
        "persona": "Ashlee Antonio",
        "total": 4,
        "online": 0,
        "taquilla": 4
      },
      {
        "persona": "Yae García",
        "total": 3,
        "online": 0,
        "taquilla": 3
      },
      {
        "persona": "Venta en línea",
        "total": 1,
        "online": 1,
        "taquilla": 0
      }
    ],
    "ordenes": 1857,
    "ordenes_online": 1052,
    "ordenes_taquilla": 805,
    "events": [
      "Juego Inaugural: Acereros vs Toros",
      "Paquete Acereros vs Toros"
    ],
    "has_paquete": true,
    "first_date": "13/02/2026",
    "last_date": "16/04/2026",
    "duration_days": 62,
    "daily": [
      {
        "date": "2026-02-13",
        "subtotal": 19800.0,
        "boletos": 20
      },
      {
        "date": "2026-03-03",
        "subtotal": 0.0,
        "boletos": 106
      },
      {
        "date": "2026-03-04",
        "subtotal": 119910.0,
        "boletos": 151
      },
      {
        "date": "2026-03-05",
        "subtotal": 77410.0,
        "boletos": 122
      },
      {
        "date": "2026-03-06",
        "subtotal": 1054633.0,
        "boletos": 1451
      },
      {
        "date": "2026-03-07",
        "subtotal": 209051.0,
        "boletos": 286
      },
      {
        "date": "2026-03-08",
        "subtotal": 86990.0,
        "boletos": 110
      },
      {
        "date": "2026-03-09",
        "subtotal": 84376.0,
        "boletos": 101
      },
      {
        "date": "2026-03-10",
        "subtotal": 84540.0,
        "boletos": 119
      },
      {
        "date": "2026-03-11",
        "subtotal": 60666.0,
        "boletos": 78
      },
      {
        "date": "2026-03-12",
        "subtotal": 40590.0,
        "boletos": 58
      },
      {
        "date": "2026-03-13",
        "subtotal": 67988.0,
        "boletos": 101
      },
      {
        "date": "2026-03-14",
        "subtotal": 40478.0,
        "boletos": 55
      },
      {
        "date": "2026-03-15",
        "subtotal": 26330.0,
        "boletos": 40
      },
      {
        "date": "2026-03-16",
        "subtotal": 31050.0,
        "boletos": 44
      },
      {
        "date": "2026-03-17",
        "subtotal": 53880.0,
        "boletos": 76
      },
      {
        "date": "2026-03-18",
        "subtotal": 38138.0,
        "boletos": 45
      },
      {
        "date": "2026-03-19",
        "subtotal": 27862.0,
        "boletos": 42
      },
      {
        "date": "2026-03-20",
        "subtotal": 38600.0,
        "boletos": 61
      },
      {
        "date": "2026-03-21",
        "subtotal": 38452.0,
        "boletos": 61
      },
      {
        "date": "2026-03-22",
        "subtotal": 10320.0,
        "boletos": 13
      },
      {
        "date": "2026-03-23",
        "subtotal": 48358.0,
        "boletos": 61
      },
      {
        "date": "2026-03-24",
        "subtotal": 78091.0,
        "boletos": 112
      },
      {
        "date": "2026-03-25",
        "subtotal": 73740.0,
        "boletos": 97
      },
      {
        "date": "2026-03-26",
        "subtotal": 92580.0,
        "boletos": 185
      },
      {
        "date": "2026-03-27",
        "subtotal": 95520.0,
        "boletos": 169
      },
      {
        "date": "2026-03-28",
        "subtotal": 43850.0,
        "boletos": 62
      },
      {
        "date": "2026-03-29",
        "subtotal": 14410.0,
        "boletos": 19
      },
      {
        "date": "2026-03-30",
        "subtotal": 55133.0,
        "boletos": 77
      },
      {
        "date": "2026-03-31",
        "subtotal": 64972.0,
        "boletos": 98
      },
      {
        "date": "2026-04-01",
        "subtotal": 66900.0,
        "boletos": 100
      },
      {
        "date": "2026-04-02",
        "subtotal": 80040.0,
        "boletos": 107
      },
      {
        "date": "2026-04-03",
        "subtotal": 73500.0,
        "boletos": 102
      },
      {
        "date": "2026-04-04",
        "subtotal": 67820.0,
        "boletos": 96
      },
      {
        "date": "2026-04-05",
        "subtotal": 43950.0,
        "boletos": 58
      },
      {
        "date": "2026-04-06",
        "subtotal": 86090.0,
        "boletos": 144
      },
      {
        "date": "2026-04-07",
        "subtotal": 81082.0,
        "boletos": 173
      },
      {
        "date": "2026-04-08",
        "subtotal": 61764.0,
        "boletos": 115
      },
      {
        "date": "2026-04-09",
        "subtotal": 99410.0,
        "boletos": 240
      },
      {
        "date": "2026-04-10",
        "subtotal": 92296.0,
        "boletos": 183
      },
      {
        "date": "2026-04-11",
        "subtotal": 103730.0,
        "boletos": 185
      },
      {
        "date": "2026-04-12",
        "subtotal": 80130.0,
        "boletos": 139
      },
      {
        "date": "2026-04-13",
        "subtotal": 191195.0,
        "boletos": 381
      },
      {
        "date": "2026-04-14",
        "subtotal": 192570.0,
        "boletos": 392
      },
      {
        "date": "2026-04-15",
        "subtotal": 162404.0,
        "boletos": 487
      },
      {
        "date": "2026-04-16",
        "subtotal": 56968.0,
        "boletos": 163
      }
    ],
    "zonas": {
      "General Preferente": {
        "boletos": 976,
        "boletos_pagados": 965,
        "boletos_cortesias": 11,
        "boletos_cortesias_online": 0,
        "boletos_cortesias_taquilla": 11,
        "boletos_promocion": 0,
        "boletos_promocion_online": 0,
        "boletos_promocion_taquilla": 0,
        "subtotal": 556742.0,
        "ticket_promedio": 576.93,
        "boletos_online": 630,
        "subtotal_online": 365400.0,
        "boletos_taquilla": 346,
        "subtotal_taquilla": 191342.0
      },
      "General Superior": {
        "boletos": 750,
        "boletos_pagados": 730,
        "boletos_cortesias": 20,
        "boletos_cortesias_online": 0,
        "boletos_cortesias_taquilla": 20,
        "boletos_promocion": 0,
        "boletos_promocion_online": 0,
        "boletos_promocion_taquilla": 0,
        "subtotal": 361550.0,
        "ticket_promedio": 495.27,
        "boletos_online": 458,
        "subtotal_online": 229000.0,
        "boletos_taquilla": 292,
        "subtotal_taquilla": 132550.0
      },
      "Jardines": {
        "boletos": 280,
        "boletos_pagados": 280,
        "boletos_cortesias": 0,
        "boletos_cortesias_online": 0,
        "boletos_cortesias_taquilla": 0,
        "boletos_promocion": 0,
        "boletos_promocion_online": 0,
        "boletos_promocion_taquilla": 0,
        "subtotal": 105260.0,
        "ticket_promedio": 375.93,
        "boletos_online": 165,
        "subtotal_online": 62700.0,
        "boletos_taquilla": 115,
        "subtotal_taquilla": 42560.0
      },
      "Palcos": {
        "boletos": 43,
        "boletos_pagados": 33,
        "boletos_cortesias": 10,
        "boletos_cortesias_online": 0,
        "boletos_cortesias_taquilla": 10,
        "boletos_promocion": 0,
        "boletos_promocion_online": 0,
        "boletos_promocion_taquilla": 0,
        "subtotal": 38460.0,
        "ticket_promedio": 1165.45,
        "boletos_online": 0,
        "subtotal_online": 0.0,
        "boletos_taquilla": 43,
        "subtotal_taquilla": 38460.0
      },
      "Palcos Superior": {
        "boletos": 45,
        "boletos_pagados": 15,
        "boletos_cortesias": 30,
        "boletos_cortesias_online": 0,
        "boletos_cortesias_taquilla": 30,
        "boletos_promocion": 0,
        "boletos_promocion_online": 0,
        "boletos_promocion_taquilla": 0,
        "subtotal": 10290.0,
        "ticket_promedio": 686.0,
        "boletos_online": 0,
        "subtotal_online": 0.0,
        "boletos_taquilla": 45,
        "subtotal_taquilla": 10290.0
      },
      "Preferente": {
        "boletos": 1091,
        "boletos_pagados": 841,
        "boletos_cortesias": 237,
        "boletos_cortesias_online": 0,
        "boletos_cortesias_taquilla": 237,
        "boletos_promocion": 13,
        "boletos_promocion_online": 0,
        "boletos_promocion_taquilla": 13,
        "subtotal": 840936.0,
        "ticket_promedio": 984.7,
        "boletos_online": 451,
        "subtotal_online": 487080.0,
        "boletos_taquilla": 640,
        "subtotal_taquilla": 353856.0
      },
      "Preferente1raBase": {
        "boletos": 437,
        "boletos_pagados": 422,
        "boletos_cortesias": 10,
        "boletos_cortesias_online": 0,
        "boletos_cortesias_taquilla": 10,
        "boletos_promocion": 5,
        "boletos_promocion_online": 0,
        "boletos_promocion_taquilla": 5,
        "subtotal": 310460.0,
        "ticket_promedio": 727.07,
        "boletos_online": 262,
        "subtotal_online": 199120.0,
        "boletos_taquilla": 175,
        "subtotal_taquilla": 111340.0
      },
      "Preferente3raBase": {
        "boletos": 479,
        "boletos_pagados": 479,
        "boletos_cortesias": 0,
        "boletos_cortesias_online": 0,
        "boletos_cortesias_taquilla": 0,
        "boletos_promocion": 0,
        "boletos_promocion_online": 0,
        "boletos_promocion_taquilla": 0,
        "subtotal": 353780.0,
        "ticket_promedio": 738.58,
        "boletos_online": 272,
        "subtotal_online": 206720.0,
        "boletos_taquilla": 207,
        "subtotal_taquilla": 147060.0
      },
      "Suite ToroGrill": {
        "boletos": 20,
        "boletos_pagados": 20,
        "boletos_cortesias": 0,
        "boletos_cortesias_online": 0,
        "boletos_cortesias_taquilla": 0,
        "boletos_promocion": 0,
        "boletos_promocion_online": 0,
        "boletos_promocion_taquilla": 0,
        "subtotal": 19800.0,
        "ticket_promedio": 990.0,
        "boletos_online": 0,
        "subtotal_online": 0.0,
        "boletos_taquilla": 20,
        "subtotal_taquilla": 19800.0
      },
      "Suites": {
        "boletos": 30,
        "boletos_pagados": 10,
        "boletos_cortesias": 20,
        "boletos_cortesias_online": 0,
        "boletos_cortesias_taquilla": 20,
        "boletos_promocion": 0,
        "boletos_promocion_online": 0,
        "boletos_promocion_taquilla": 0,
        "subtotal": 6860.0,
        "ticket_promedio": 686.0,
        "boletos_online": 0,
        "subtotal_online": 0.0,
        "boletos_taquilla": 30,
        "subtotal_taquilla": 6860.0
      },
      "Superior": {
        "boletos": 1489,
        "boletos_pagados": 1055,
        "boletos_cortesias": 431,
        "boletos_cortesias_online": 0,
        "boletos_cortesias_taquilla": 431,
        "boletos_promocion": 3,
        "boletos_promocion_online": 1,
        "boletos_promocion_taquilla": 2,
        "subtotal": 861970.0,
        "ticket_promedio": 814.72,
        "boletos_online": 513,
        "subtotal_online": 486400.0,
        "boletos_taquilla": 976,
        "subtotal_taquilla": 375570.0
      },
      "Superior1raBase": {
        "boletos": 538,
        "boletos_pagados": 530,
        "boletos_cortesias": 2,
        "boletos_cortesias_online": 0,
        "boletos_cortesias_taquilla": 2,
        "boletos_promocion": 6,
        "boletos_promocion_online": 0,
        "boletos_promocion_taquilla": 6,
        "subtotal": 324450.0,
        "ticket_promedio": 605.32,
        "boletos_online": 262,
        "subtotal_online": 165060.0,
        "boletos_taquilla": 276,
        "subtotal_taquilla": 159390.0
      },
      "Superior3raBase": {
        "boletos": 717,
        "boletos_pagados": 691,
        "boletos_cortesias": 24,
        "boletos_cortesias_online": 0,
        "boletos_cortesias_taquilla": 24,
        "boletos_promocion": 2,
        "boletos_promocion_online": 0,
        "boletos_promocion_taquilla": 2,
        "subtotal": 429089.0,
        "ticket_promedio": 619.18,
        "boletos_online": 403,
        "subtotal_online": 253890.0,
        "boletos_taquilla": 314,
        "subtotal_taquilla": 175199.0
      },
      "ToroBar": {
        "boletos": 123,
        "boletos_pagados": 72,
        "boletos_cortesias": 51,
        "boletos_cortesias_online": 0,
        "boletos_cortesias_taquilla": 51,
        "boletos_promocion": 0,
        "boletos_promocion_online": 0,
        "boletos_promocion_taquilla": 0,
        "subtotal": 50400.0,
        "ticket_promedio": 700.0,
        "boletos_online": 0,
        "subtotal_online": 0.0,
        "boletos_taquilla": 123,
        "subtotal_taquilla": 50400.0
      },
      "ToroGrill": {
        "boletos": 42,
        "boletos_pagados": 42,
        "boletos_cortesias": 0,
        "boletos_cortesias_online": 0,
        "boletos_cortesias_taquilla": 0,
        "boletos_promocion": 0,
        "boletos_promocion_online": 0,
        "boletos_promocion_taquilla": 0,
        "subtotal": 27720.0,
        "ticket_promedio": 660.0,
        "boletos_online": 0,
        "subtotal_online": 0.0,
        "boletos_taquilla": 42,
        "subtotal_taquilla": 27720.0
      },
      "Zona Móbil": {
        "boletos": 25,
        "boletos_pagados": 20,
        "boletos_cortesias": 5,
        "boletos_cortesias_online": 0,
        "boletos_cortesias_taquilla": 5,
        "boletos_promocion": 0,
        "boletos_promocion_online": 0,
        "boletos_promocion_taquilla": 0,
        "subtotal": 19800.0,
        "ticket_promedio": 990.0,
        "boletos_online": 0,
        "subtotal_online": 0.0,
        "boletos_taquilla": 25,
        "subtotal_taquilla": 19800.0
      }
    }
  }
}